fcmeans_softwrd/__init__.py
fcmeans_softwrd/cli.py
fcmeans_softwrd/main.py
fcmeans_softwrd-0.0.2.dist-info/METADATA
fcmeans_softwrd-0.0.2.dist-info/WHEEL
fcmeans_softwrd-0.0.2.dist-info/top_level.txt
fcmeans_softwrd-0.0.2.dist-info/RECORD
