Metadata-Version: 2.1
Name: fcmeans_softwrd
Version: 0.0.2
Summary: A Python package of Fuzzy-C-means algorithm for softwrd data and ml team.
Home-page: https://github.com/softwrdai/ml-fuzzy-c-means
Author: Kazi Ferdous Mahin, Proshanta Kumer Das
Author-email: mahin@softwrd.ai, proshanto@softwrd.ai
Classifier: Programming Language :: Python :: 3
Classifier: License :: OSI Approved :: Apache Software License
Classifier: Operating System :: Microsoft :: Windows
Requires-Python: >=3.9
Requires-Dist: boto3
Requires-Dist: pydantic
Requires-Dist: tqdm
Requires-Dist: typer
